README.md
setup.cfg
setup.py
kd_distributions/Binomialdistribution.py
kd_distributions/Gaussiandistribution.py
kd_distributions/Generaldistribution.py
kd_distributions/__init__.py
kd_distributions.egg-info/PKG-INFO
kd_distributions.egg-info/SOURCES.txt
kd_distributions.egg-info/dependency_links.txt
kd_distributions.egg-info/not-zip-safe
kd_distributions.egg-info/top_level.txt