Metadata-Version: 1.0
Name: kd-distributions
Version: 0.1
Summary: Gaussian and Binomial distributions
Home-page: UNKNOWN
Author: Kaustubh Dixit
Author-email: kdkishu335@gmail.com
License: UNKNOWN
Platform: UNKNOWN
